CHANGES.txt
MANIFEST.in
README.txt
setup.py
corejet/__init__.py
corejet.testrunner.egg-info/PKG-INFO
corejet.testrunner.egg-info/SOURCES.txt
corejet.testrunner.egg-info/dependency_links.txt
corejet.testrunner.egg-info/entry_points.txt
corejet.testrunner.egg-info/namespace_packages.txt
corejet.testrunner.egg-info/not-zip-safe
corejet.testrunner.egg-info/requires.txt
corejet.testrunner.egg-info/top_level.txt
corejet/testrunner/__init__.py
corejet/testrunner/filesource.py
corejet/testrunner/formatter.py
corejet/testrunner/recipe.py
corejet/testrunner/runner.py