Metadata-Version: 1.0
Name: corejet.testrunner
Version: 1.0.1
Summary: A test runner which can output an XML report compatible with JUnit and Hudson/Jenkins as well as XML and HTML reports compatible with the CoreJet BDD standard
Home-page: http://corejet.org
Author: Martin Aspeli
Author-email: optilude@gmail.com
License: ZPL 2.1
Keywords: hudson jenkins junit xml corejet zope.testing
Platform: UNKNOWN
Classifier: Programming Language :: Python
